{"is_source_file": false, "format": "", "description": "", "external_files": [], "external_methods": [], "published": [], "classes": [], "methods": [], "calls": [], "search-terms": [], "state": 2, "file_id": 13, "knowledge_revision": 28, "git_revision": "32216a410b9dba84e6f1605e577d14a85aacebbd", "hash": "699579880a795350891cafc998a3ec79", "format-version": 4, "code-base-name": "frontend_app", "filename": "frontend_app/android/build.gradle.kts", "revision_history": [{"28": "32216a410b9dba84e6f1605e577d14a85aacebbd"}]}